llutils/Greetings.py
llutils/HPC.py
llutils/__init__.py
llutils/colors.py
tests/__init__.py
tests/test_greetings.py
llutils-0.0.2.dist-info/LICENSE
llutils-0.0.2.dist-info/METADATA
llutils-0.0.2.dist-info/WHEEL
llutils-0.0.2.dist-info/top_level.txt
llutils-0.0.2.dist-info/RECORD
