Metadata-Version: 2.1
Name: llutils
Version: 0.0.2
Summary: A collection of functions for various purposes
Home-page: https://github.com/LukasLeindals/llutils
Author-email: luke.leindance@gmail.com
License: UNKNOWN
Keywords: utils
Platform: UNKNOWN
Classifier: License :: OSI Approved :: MIT License
Classifier: Programming Language :: Python :: 3 :: Only
License-File: LICENSE
